
{
  "type": "FeatureCollection",
  "features": [
    {
      "type": "Feature",
      "properties": {
        "name": "Nahua Store",
        "address": "Jr Raimondi 283, Iquitos, Peru",
        "opening_hours": "Lun-Dom 8am - 8pm"
      },
      "geometry": {
        "coordinates": [
          -73.24291973932412,
          -3.7483738934132873
        ],
        "type": "Point"
      }
    },
    {
      "type": "Feature",
      "properties": {
        "name": "Hotel de Turistas",
        "address": "Malecón Tarapaca 128, Iquitos, Peru",
        "opening_hours": "Lun-Sab 8am - 6pm"
      },
      "geometry": {
        "coordinates": [
          -73.2431444466135,
          -3.7501529908466864
        ],
        "type": "Point"
      }
    },
    {
      "type": "Feature",
      "properties": {
        "name": "Oficina iPerú Iquitos",
        "address": "JR. Napo 161 , Iquitos, Peru",
        "opening_hours": "Lun-Sab 9am - 6pm; Dom: 9am - 1pm"
      },
      "geometry": {
        "coordinates": [
          -73.2436095460138,
          -3.74970790945369
        ],
        "type": "Point"
      }
    }
    
  ]
}